aoc/__init__.py
aoc/library.py
aoc/objects/event.py
aoc/objects/helper.py
aoc/objects/task.py
tests/__init__.py
tests/test_manual.py
tests/test_multiple.py
tests/test_single.py
aoc_library-0.1.4.dist-info/LICENSE.md
aoc_library-0.1.4.dist-info/METADATA
aoc_library-0.1.4.dist-info/WHEEL
aoc_library-0.1.4.dist-info/top_level.txt
aoc_library-0.1.4.dist-info/RECORD
